smolllm/__init__.py
smolllm/balancer.py
smolllm/core.py
smolllm/display.py
smolllm/log.py
smolllm/metrics.py
smolllm/provider_config.py
smolllm/providers.py
smolllm/py.typed
smolllm/request.py
smolllm/stream.py
smolllm/types.py
smolllm/utils.py
smolllm-0.5.0.dist-info/METADATA
smolllm-0.5.0.dist-info/WHEEL
smolllm-0.5.0.dist-info/entry_points.txt
smolllm-0.5.0.dist-info/licenses/LICENSE
smolllm-0.5.0.dist-info/RECORD
