Metadata-Version: 2.4
Name: smolllm
Version: 0.5.0
Summary: A minimal Python library for interacting with various LLM providers
Project-URL: Homepage, https://github.com/RoCry/smolllm
Project-URL: Repository, https://github.com/RoCry/smolllm.git
Author-email: RoCry <crysheen@gmail.com>
License: MIT
License-File: LICENSE
Keywords: ai,anthropic,gemini,llm,openai
Classifier: Development Status :: 4 - Beta
Classifier: Intended Audience :: Developers
Classifier: License :: OSI Approved :: MIT License
Classifier: Programming Language :: Python :: 3
Classifier: Programming Language :: Python :: 3.13
Classifier: Topic :: Software Development :: Libraries :: Python Modules
Requires-Python: >=3.13
Requires-Dist: httpx>=0.28.1
Requires-Dist: python-dotenv>=1.0.1
Requires-Dist: rich>=13.9.4
Provides-Extra: dev
Requires-Dist: build>=1.2.2; extra == 'dev'
Requires-Dist: twine>=4.0.2; extra == 'dev'
Provides-Extra: test
Requires-Dist: pytest-asyncio>=1.1.0; extra == 'test'
Requires-Dist: pytest>=8.3.5; extra == 'test'
